README.md
setup.py
pmo/__init__.py
pmo/__main__.py
pmo/cli.py
pmo/datetime_util.py
pmo/estimate_time.py
pmo/syntax.py
pmo/syntax_util.py
pmomake.egg-info/PKG-INFO
pmomake.egg-info/SOURCES.txt
pmomake.egg-info/dependency_links.txt
pmomake.egg-info/entry_points.txt
pmomake.egg-info/requires.txt
pmomake.egg-info/top_level.txt
test/test_datetime_util.py
test/test_syntax_util.py