Metadata-Version: 1.0
Name: pmomake
Version: 1.0.4
Summary: Makefile for PMO
Home-page: https://pypi.python.org/pypi/pmomake
Author: qorzj
Author-email: inull@qq.com
License: MIT
Keywords: pmomake pmo gantt
Platform: any
